{
  "episode": {
    "duration": "1:40",
    "id": "r7LVaWeM_bg",
    "index": 9,
    "name": "Bref. J'ai recroisé cette fille.",
    "slug": "brefJaiRecroiseCetteFille"
  },
  "subtitles": [
    {
      "content": "Bref, ce matin-là, je me suis réveillé\navec une envie pressante d'aller\naux toilettes.",
      "index": 0,
      "start": 1
    },
    {
      "content": "Juste à temps, je me suis rendu compte\nqu'il y avait plus de papier toilette,\nplus de sopalin, plus de Kleenex\net j'avais pas encore fini ce magazine.",
      "index": 1,
      "start": 4
    },
    {
      "content": "Je suis parti au supermarché en acheter.",
      "index": 2,
      "start": 9
    },
    {
      "content": "Et là, j'ai croisé cette fille.",
      "index": 3,
      "start": 11
    },
    {
      "content": "C'était une fille que\nj'avais draguée à une soirée.",
      "index": 4,
      "start": 12
    },
    {
      "content": "Mon cul m'a dit cours,\nmon cœur m'a dit reste.",
      "index": 5,
      "start": 13
    },
    {
      "content": "Elle m'a dit:\n— Hey, Vincent.\nJe m'appelle pas Vincent. J'ai rien dit.",
      "index": 6,
      "start": 15
    },
    {
      "content": "À ce moment précis, je me suis rendu\ncompte que: un, j'étais pas lavé, deux,\nj'étais mal habillé, trois, j'avais des\ncacas d'yeux au coin des yeux et quatre, un",
      "index": 7,
      "start": 17
    },
    {
      "content": "paquet de rouleaux de PQ dans les mains.",
      "index": 8,
      "start": 24
    },
    {
      "content": "Je me suis dit:\n— C'est pas\nvrai, qu'est-ce qu'elle fout là ?",
      "index": 9,
      "start": 25
    },
    {
      "content": "Je lui ai dit:\n— Hey, mais qu'est-ce que tu fais là ?",
      "index": 10,
      "start": 26
    },
    {
      "content": "On a discuté, elle m'a fait une blague,\nc'était pas marrant, j'ai rigolé.",
      "index": 11,
      "start": 27
    },
    {
      "content": "En rigolant, je me suis rendu compte\nque cinq, j'avais mauvaise haleine.",
      "index": 12,
      "start": 30
    },
    {
      "content": "On a parlé de tout et de rien,\nsurtout de rien.",
      "index": 13,
      "start": 33
    },
    {
      "content": "— Elle me dit ça, il faut pas le manger,\nc'est bourré de trucs mauvais et tout.",
      "index": 14,
      "start": 35
    },
    {
      "content": "— Alors attends, ça c'était ma...",
      "index": 15,
      "start": 38
    },
    {
      "content": "À un moment donné,\nelle s'est mordillée la lèvre.",
      "index": 16,
      "start": 42
    },
    {
      "content": "J'ai eu envie de:\nL'inviter à boire un verre. L'inviter au resto. L'inviter\nau cinéma. La raccompagner\nchez elle. Coucher avec elle.",
      "index": 17,
      "start": 45
    },
    {
      "content": "Qu'elle me demande si c'est sérieux\nentre nous. Mmanger des glaces avec elle.",
      "index": 18,
      "start": 48
    },
    {
      "content": "S'allonger dans l'herbe. Lui présenter ma famille.",
      "index": 19,
      "start": 50
    },
    {
      "content": "Partir en vacances avec elle.\nEmménager avec elle.",
      "index": 20,
      "start": 51
    },
    {
      "content": "La demander en mariage. Acheter\nune maison avec elle. Lui demander:",
      "index": 21,
      "start": 53
    },
    {
      "content": "— Ça va ?\nQu'elle me réponde:",
      "index": 22,
      "start": 54
    },
    {
      "content": "— Je suis enceinte.\nQu'elle me dise:\n— C'est des jumeaux.",
      "index": 23,
      "start": 55
    },
    {
      "content": "Qu'on se demande comment on va les appeler.",
      "index": 24,
      "start": 56
    },
    {
      "content": "Elle me dit:\n— T'es pas d'accord ?",
      "index": 25,
      "start": 57
    },
    {
      "content": "J'ai répondu:\n— Euh, Grégoire et Julie.\n— Quoi ?",
      "index": 26,
      "start": 59
    },
    {
      "content": "Je lui ai dit que c'était\nle nom de mes poissons.",
      "index": 27,
      "start": 61
    },
    {
      "content": "Elle m'a demandé ce\nque c'était comme poisson.",
      "index": 28,
      "start": 62
    },
    {
      "content": "J'ai dit n'importe quoi.\n— Des poissons clowns\nElle m'a répondu:\n— Mais c'est génial !",
      "index": 29,
      "start": 64
    },
    {
      "content": "Merde.\n— Comme Nemo.",
      "index": 30,
      "start": 66
    },
    {
      "content": "Merde.",
      "index": 31,
      "start": 67
    },
    {
      "content": "Je lui ai dit:\n— Tu pourras passer les voir un jour.",
      "index": 32,
      "start": 68
    },
    {
      "content": "Elle a souri.\nElle a repris mon numéro.",
      "index": 33,
      "start": 69
    },
    {
      "content": "Mon corps envoyait des signaux pressants.",
      "index": 34,
      "start": 71
    },
    {
      "content": "Elle m'a demandé:\n— Tu t'appelles\nVincent comment déjà ?",
      "index": 35,
      "start": 72
    },
    {
      "content": "— Euh, Dubois.",
      "index": 36,
      "start": 74
    },
    {
      "content": "— Bon. Salut.\n— Salut.",
      "index": 37,
      "start": 76
    },
    {
      "content": "Elle est partie en souriant.\nJe suis partie en courance.",
      "index": 38,
      "start": 78
    },
    {
      "content": "Voilà.",
      "index": 39,
      "start": 80
    },
    {
      "content": "Maintenant, je m'appelle Vincent Dubois\net j'ai deux poissons clowns.",
      "index": 40,
      "start": 80
    },
    {
      "content": "Et il faut que je fasse une lessive.",
      "index": 41,
      "start": 82
    },
    {
      "content": "Bref, j'ai recroisé cette fille.",
      "index": 42,
      "start": 84
    },
    {
      "content": "— Putain...",
      "index": 43,
      "start": 96
    }
  ]
}
