{
  "episode": {
    "duration": "2:02",
    "id": "m5Ezt99WggY",
    "index": 51,
    "name": "Bref. Mon frère a quelqu'un.",
    "slug": "brefMonFrereAQuelquun"
  },
  "subtitles": [
    {
      "content": "— Tu sais les pushcar, le Sud de l'Inde,\nle Kerala...",
      "index": 0,
      "start": 0
    },
    {
      "content": "Bref. Lui, c'est mon frère.\nIl a toujours été là pour moi.",
      "index": 1,
      "start": 4
    },
    {
      "content": "— Ouais ?\n— Elle m'a quitté.\n— J'arrive.",
      "index": 2,
      "start": 6
    },
    {
      "content": "— Ouais ?\n— J'ai eu mon permis.\n— J'arrive.",
      "index": 3,
      "start": 7
    },
    {
      "content": "— J'arrive.\n— J'arrive.",
      "index": 4,
      "start": 9
    },
    {
      "content": "Jusqu'au jour où il s'est fait\nlarguer, du coup, il allait pas bien.",
      "index": 5,
      "start": 10
    },
    {
      "content": "Et moi, j'ai essayé d'être là pour lui.",
      "index": 6,
      "start": 12
    },
    {
      "content": "— Vu que t'es pas bien, je t'ai fait une patate\navec des bras\nMais je galérais.",
      "index": 7,
      "start": 13
    },
    {
      "content": "Il pensait encore à son ex, Maud.",
      "index": 8,
      "start": 19
    },
    {
      "content": "Maud, c'est le genre de meuf qui organise\ndes soirées pour pouvoir dire:",
      "index": 9,
      "start": 22
    },
    {
      "content": "— C'est ma soirée, ou c'est pas ma soirée.",
      "index": 10,
      "start": 24
    },
    {
      "content": "Quand elle organise une soirée,\nelle ORGANISE une soirée.",
      "index": 11,
      "start": 25
    },
    {
      "content": "Elle dit aux gens où ils\ndoivent s'asseoir.",
      "index": 12,
      "start": 27
    },
    {
      "content": "— Toi, t'es là.\nElle crie:\n— Ouaaaaais.",
      "index": 13,
      "start": 28
    },
    {
      "content": "Elle est débordée et elle fait\nen sorte qu'on voit qu'elle est débordée.",
      "index": 14,
      "start": 30
    },
    {
      "content": "— Non, je sais pas, je suis débordée.",
      "index": 15,
      "start": 32
    },
    {
      "content": "Elle dit pardon de la façon\nla plus énervante du monde.",
      "index": 16,
      "start": 33
    },
    {
      "content": "— Pardon.\nElle crie ouais.\n— Ouaaaaais.",
      "index": 17,
      "start": 34
    },
    {
      "content": "Elle passe sa soirée à prendre\ndes photos pour les mettre sur Facebook\npour montrer qu'elle a fait une soirée.",
      "index": 18,
      "start": 35
    },
    {
      "content": "Elle tague les gens qui n'ont pas pu venir\nà la soirée pour qu'ils voient\nque c'était une bonne soirée.\nElle part souvent du principe que...",
      "index": 19,
      "start": 39
    },
    {
      "content": "— Moi, je pars du principe que...\nElle fait des cakes aux olives.",
      "index": 20,
      "start": 43
    },
    {
      "content": "Elle crie ouais.\n— Ouaaaaais.\nElle range alors qu'on est encore là.",
      "index": 21,
      "start": 44
    },
    {
      "content": "— Pardon.",
      "index": 22,
      "start": 47
    },
    {
      "content": "À la fin, elle dit toujours:\n— C'est la dernière fois que je fais une soirée.",
      "index": 23,
      "start": 49
    },
    {
      "content": "— Je suis crevée.",
      "index": 24,
      "start": 52
    },
    {
      "content": "Et la semaine d'après :\n— Ouaaaaais.\nElle refait une soirée.",
      "index": 25,
      "start": 53
    },
    {
      "content": "Je me suis dit qu'il fallait\nqu'ils se croisent par hasard.",
      "index": 26,
      "start": 56
    },
    {
      "content": "Mon frère était là et dans 15 minutes,\nMaud allait arriver par hasard.",
      "index": 27,
      "start": 58
    },
    {
      "content": "— Ouais, Maud, ça te dirait\nde passer à la maison ?",
      "index": 28,
      "start": 61
    },
    {
      "content": "— On pourrait parler de ta dernière soirée.",
      "index": 29,
      "start": 63
    },
    {
      "content": "Sauf que mon frère avait la tête de\nquelqu'un qui avait rencontré quelqu'un.",
      "index": 30,
      "start": 65
    },
    {
      "content": "J'ai dit:\n— T'as rencontré quelqu'un ?\nIl m'a dit:\n— Non.",
      "index": 31,
      "start": 67
    },
    {
      "content": "J'ai dit:\n— T'as rencontré quelqu'un ?\nIl m'a dit:\n— Oui.",
      "index": 32,
      "start": 69
    },
    {
      "content": "J'ai dit:\n— C'est Maud ?\nIl m'a dit:\n— Bha, non.",
      "index": 33,
      "start": 71
    },
    {
      "content": "Merde.",
      "index": 34,
      "start": 73
    },
    {
      "content": "J'ai voulu savoir qui c'était.",
      "index": 35,
      "start": 74
    },
    {
      "content": "— Elle est brune ?\n— Non.",
      "index": 36,
      "start": 76
    },
    {
      "content": "— Elle a un rire énervant ?\n— Non.",
      "index": 37,
      "start": 78
    },
    {
      "content": "— Elle dit lol dans la vraie vie ?\n— Non.",
      "index": 38,
      "start": 80
    },
    {
      "content": "— Grande ?\n— Petite ?\n— Cheloue ?\n— Alcolique ?",
      "index": 39,
      "start": 81
    },
    {
      "content": "— Non.\n— Non.\n— Non.\n— Non.",
      "index": 40,
      "start": 84
    },
    {
      "content": "Alors, ça peut être que...",
      "index": 41,
      "start": 89
    },
    {
      "content": "— Hey salut Maud.\n— Salut.\n— C'est cool que tu sois là.",
      "index": 42,
      "start": 95
    },
    {
      "content": "— Justement, il y a Keyvan qui est passé. Entre.",
      "index": 43,
      "start": 96
    },
    {
      "content": "Bref, mon frère a quelqu'un.",
      "index": 44,
      "start": 102
    },
    {
      "content": "— Il était à quoi alors ce cake\nsalé la dernière fois ?",
      "index": 45,
      "start": 109
    },
    {
      "content": "— Aux olives.\n— Aux olives.",
      "index": 46,
      "start": 112
    }
  ]
}
