{
  "episode": {
    "duration": "1:36",
    "id": "LZQUFY0W_lY",
    "index": 64,
    "name": "Bref. J'ai fait un dessin.",
    "slug": "brefJaiFaitUnDessin",
    "viewCount": 6204629
  },
  "subtitles": [
    {
      "content": "Bref. Ça, c'est un dessin que j'ai fait\nquand j'avais six ans.",
      "index": 0,
      "start": 1,
      "stop": 3
    },
    {
      "content": "Ma mère m'avait dit: \"Va\nlà-haut faire un dessin.\"\nAlors, je me suis dessiné\nen haut en train de faire un dessin.",
      "index": 1,
      "start": 3,
      "stop": 6
    },
    {
      "content": "Sur le toit, il y avait des tuiles,\nmais c'était trop relou à faire.",
      "index": 2,
      "start": 6,
      "stop": 8
    },
    {
      "content": "Alors, au bout d'un moment,\nj'ai mis des cheveux.",
      "index": 3,
      "start": 8,
      "stop": 9
    },
    {
      "content": "Mais comme c'était pas logique,\nune maison avec des cheveux,\nje lui ai rajouté des oreilles.",
      "index": 4,
      "start": 9,
      "stop": 12
    },
    {
      "content": "On n'avait pas de cheminée,\nmais comme je sais faire\ndes cheminées, j'ai fait une cheminée.\nDehors, c'était une belle journée.",
      "index": 5,
      "start": 12,
      "stop": 15
    },
    {
      "content": "Il y avait un soleil dans le coin\navec un grand rayon, un petit rayon,\nun grand rayon, un petit rayon, un grand rayon,\net un petit rayon.",
      "index": 6,
      "start": 15,
      "stop": 19
    },
    {
      "content": "et un rectangle bleu pour faire le ciel.",
      "index": 7,
      "start": 19,
      "stop": 20
    },
    {
      "content": "En dessous du ciel, il y avait un avion\navec une aile en bas et une aile en haut.",
      "index": 8,
      "start": 20,
      "stop": 22
    },
    {
      "content": "Et derrière l'avion, il y avait\nun nuage, un autre nuage.",
      "index": 9,
      "start": 22,
      "stop": 24
    },
    {
      "content": "Et après, je me suis rendu compte que\nsi je mettais quatre pattes et deux yeux\nà un nuage, ça faisait un mouton.\nJ'ai fait un mouton.",
      "index": 10,
      "start": 24,
      "stop": 27
    },
    {
      "content": "Mais comme les moutons volant,\nça n'existe pas, je l'ai attaché au ciel.",
      "index": 11,
      "start": 27,
      "stop": 30
    },
    {
      "content": "Dehors, il y avait mon père.\nIl était au travail.",
      "index": 12,
      "start": 30,
      "stop": 31
    },
    {
      "content": "Il n'avait pas de chaussures parce\nqu'il les avait oubliées à la maison.",
      "index": 13,
      "start": 31,
      "stop": 33
    },
    {
      "content": "Il y avait aussi trois bras parce qu'à\nl'époque, il avait demandé sa mutation.",
      "index": 14,
      "start": 33,
      "stop": 35
    },
    {
      "content": "Et une épée parce que je savais pas\nquel métier il faisait.",
      "index": 15,
      "start": 35,
      "stop": 37
    },
    {
      "content": "Au-dessus de lui,\nil y avait des oiseaux en V.",
      "index": 16,
      "start": 37,
      "stop": 38
    },
    {
      "content": "D'ailleurs, aux fenêtres de la maison,\nil y avait des rideaux en B.",
      "index": 17,
      "start": 38,
      "stop": 40
    },
    {
      "content": "Dans la maison, il y avait ma mère.\nElle s'était faite belle.",
      "index": 18,
      "start": 40,
      "stop": 42
    },
    {
      "content": "Elle avait deux cheveux, une jupe\nen triangle et des boucles d'oreilles\nplus grosses que sa tête.",
      "index": 19,
      "start": 42,
      "stop": 45
    },
    {
      "content": "Elle tenait mon frère\npar la main, mais je l'ai gommé.",
      "index": 20,
      "start": 45,
      "stop": 46
    },
    {
      "content": "Comme ça, je pouvais récupérer son vélo.",
      "index": 21,
      "start": 46,
      "stop": 48
    },
    {
      "content": "Dehors, il y avait un chemin avec de\nl'herbe en M. Il y avait aussi un dragon.",
      "index": 22,
      "start": 48,
      "stop": 50
    },
    {
      "content": "Mais vu que je savais pas dessiner\nles dragons, je l'ai fait très loin.",
      "index": 23,
      "start": 50,
      "stop": 52
    },
    {
      "content": "Mais dans ma tête, il ressemblait à ça.",
      "index": 24,
      "start": 52,
      "stop": 53
    },
    {
      "content": "Dans le jardin, il y avait\nmon frère avec ses potes.",
      "index": 25,
      "start": 53,
      "stop": 56
    },
    {
      "content": "Ils se cachaient pour fumer des haches.",
      "index": 26,
      "start": 56,
      "stop": 57
    },
    {
      "content": "C'était vachement dangereux\net il m'avait dit de pas le répéter.",
      "index": 27,
      "start": 57,
      "stop": 59
    },
    {
      "content": "Attends.",
      "index": 28,
      "start": 59,
      "stop": 60
    },
    {
      "content": "Si ma mère m'avait demandé de monter faire\nun dessin pendant que mon père était loin\net surtout, si mon frère était\ndans le jardin, qui est-ce qui tenait",
      "index": 29,
      "start": 60,
      "stop": 65
    },
    {
      "content": "la main de ma mère dans ma maison ?\nCes chaussures, elles sont pas à mon père.",
      "index": 30,
      "start": 65,
      "stop": 69
    },
    {
      "content": "Bref, je crois que j'ai un secret.",
      "index": 31,
      "start": 69,
      "stop": 74
    },
    {
      "content": "— Qu'est-ce que tu fais ?",
      "index": 32,
      "start": 74,
      "stop": 75
    },
    {
      "content": "— Ça, c'est un avion, ça,\nc'est le dragon et ça, c'est\ntoi qui tient la main du monsieur.\n— Je vais le montrer à papa en rentrant.",
      "index": 33,
      "start": 75,
      "stop": 81
    },
    {
      "content": "— Mais quel monsieur ? Il y a pas de monsieur.",
      "index": 34,
      "start": 82,
      "stop": 84
    },
    {
      "content": "— Allez, gomme le monsieur.",
      "index": 35,
      "start": 84,
      "stop": 86
    },
    {
      "content": "— Et on va t'acheter un vélo.",
      "index": 36,
      "start": 87,
      "stop": 89
    }
  ]
}
