{
  "episode": {
    "duration": "2:01",
    "id": "8matlnmBY98",
    "index": 68,
    "name": "Bref. J'ai passé un coup de fil.",
    "slug": "brefJaiPasseUnCoupDeFil",
    "viewCount": 5402932
  },
  "subtitles": [
    {
      "content": "Bref, ce soir-là,\non devait aller au cinéma.",
      "index": 0,
      "start": 2,
      "stop": 3
    },
    {
      "content": "J'ai appelé Ben pour savoir\nquel film on allait voir.",
      "index": 1,
      "start": 3,
      "stop": 5
    },
    {
      "content": "Je suis tombé sur sa messagerie,\nje lui ai laissé un message.",
      "index": 2,
      "start": 5,
      "stop": 7
    },
    {
      "content": "— Ouais Ben, dis-moi, je voulais savoir\nquel film on allait...",
      "index": 3,
      "start": 7,
      "stop": 9
    },
    {
      "content": "— Ah attends, c'est toi qui me rappelle.",
      "index": 4,
      "start": 9,
      "stop": 10
    },
    {
      "content": "J'ai voulu prendre l'appel,\nmais comme d'hab, ça marchait pas.",
      "index": 5,
      "start": 10,
      "stop": 12
    },
    {
      "content": "J'ai rappuyé, j'ai dit:\n— Allô ?\nIl avait raccroché.",
      "index": 6,
      "start": 12,
      "stop": 14
    },
    {
      "content": "J'ai rappelé. Je suis\ntombé sur sa messagerie.",
      "index": 7,
      "start": 14,
      "stop": 17
    },
    {
      "content": "— Bon bha, rappelle-moi,\nj'arrive pas à te joindre.",
      "index": 8,
      "start": 17,
      "stop": 19
    },
    {
      "content": "J'ai écouté ma messagerie.",
      "index": 9,
      "start": 19,
      "stop": 21
    },
    {
      "content": "— Bon bha, rappelle-moi,\nj'arrive pas à te joindre.",
      "index": 10,
      "start": 21,
      "stop": 22
    },
    {
      "content": "J'ai compris qu'on était piégé.\nJ'ai décidé d'attendre qu'il me rappelle.",
      "index": 11,
      "start": 22,
      "stop": 25
    },
    {
      "content": "Je me suis dit qu'il devait faire\nla même chose, alors je l'ai rappelé.",
      "index": 12,
      "start": 25,
      "stop": 27
    },
    {
      "content": "Je suis tombé sur sa messagerie.",
      "index": 13,
      "start": 27,
      "stop": 29
    },
    {
      "content": "— Vous êtes bien sur le répondeur de Ben,\nlaissez moi un message. Tchao.",
      "index": 14,
      "start": 29,
      "stop": 30
    },
    {
      "content": "J'ai raccroché, mon téléphone a sonné.\n— Allô ?",
      "index": 15,
      "start": 30,
      "stop": 32
    },
    {
      "content": "— Ouais.",
      "index": 16,
      "start": 32,
      "stop": 32
    },
    {
      "content": "C'était Baptiste qui me disait\nqu'il arrivait pas à joindre Ben.",
      "index": 17,
      "start": 32,
      "stop": 34
    },
    {
      "content": "— J'arrive pas à joindre Ben.",
      "index": 18,
      "start": 34,
      "stop": 35
    },
    {
      "content": "Pendant que je parle avec lui,\nBen m'a rappelé.",
      "index": 19,
      "start": 35,
      "stop": 36
    },
    {
      "content": "— Attends, il m'appelle là.\n— Cool.",
      "index": 20,
      "start": 36,
      "stop": 37
    },
    {
      "content": "— Dis-lui que j'essaie de le joindre.",
      "index": 21,
      "start": 37,
      "stop": 39
    },
    {
      "content": "J'ai mis Baptiste en attente.\n— Allô ?",
      "index": 22,
      "start": 39,
      "stop": 40
    },
    {
      "content": "— Ouais, c'était pour savoir quel film...\n— Attends, y a Julien qui m'appelle.",
      "index": 23,
      "start": 40,
      "stop": 42
    },
    {
      "content": "Il m'a mis en attente.\n— Ouais, Julien.",
      "index": 24,
      "start": 42,
      "stop": 44
    },
    {
      "content": "— Ouais y a Baptiste qui essaye de te joindre.",
      "index": 25,
      "start": 44,
      "stop": 45
    },
    {
      "content": "J'ai repris Baptiste.\n— Tu lui as dit que j'essaye de le joindre ?",
      "index": 26,
      "start": 45,
      "stop": 47
    },
    {
      "content": "Je lui ai dit que je n'avais pas eu\nle temps vu que Julien l'avait appelé.",
      "index": 27,
      "start": 47,
      "stop": 49
    },
    {
      "content": "Mon téléphone fixe a sonné.",
      "index": 28,
      "start": 49,
      "stop": 50
    },
    {
      "content": "— Y a mon téléphone fixe\nqui sonne, c'est chelou.",
      "index": 29,
      "start": 50,
      "stop": 51
    },
    {
      "content": "C'est qui ?\nAllô ?",
      "index": 30,
      "start": 51,
      "stop": 54
    },
    {
      "content": "C'était Charles, il appelait d'une cabine.\n— Ouais, c'est Charles.",
      "index": 31,
      "start": 54,
      "stop": 56
    },
    {
      "content": "— Putain, j'ai perdu mon portable\net t'es le seul qui est dans l'annuaire.",
      "index": 32,
      "start": 56,
      "stop": 58
    },
    {
      "content": "— Ouais, ouais.\n— Oui, oui.",
      "index": 33,
      "start": 59,
      "stop": 59
    },
    {
      "content": "— Oui, oui.\n— Oui, C'est qui ?",
      "index": 34,
      "start": 59,
      "stop": 60
    },
    {
      "content": "J'ai eu un double appel de Xavier.\n— Ouais Christophe, c'est Xavier.",
      "index": 35,
      "start": 60,
      "stop": 62
    },
    {
      "content": "Je ne connaissais pas de Xavier\net je m'appelais pas Christophe,\nalors j'ai dit:\n— Désolé, c'est une erreur.",
      "index": 36,
      "start": 62,
      "stop": 65
    },
    {
      "content": "Charles a dit:\n— Tu peux dire\nà Baptiste que je vais être en retard ?",
      "index": 37,
      "start": 65,
      "stop": 67
    },
    {
      "content": "— Charles sera en retard.",
      "index": 38,
      "start": 67,
      "stop": 69
    },
    {
      "content": "— C'est qui Charles ?\nCharles a dit merci et a raccroché.",
      "index": 39,
      "start": 69,
      "stop": 72
    },
    {
      "content": "Pendant ce temps,\nBen avait fini avec Julien.",
      "index": 40,
      "start": 72,
      "stop": 73
    },
    {
      "content": "J'ai raccroché avec Xavier\net j'ai récupéré Baptiste.",
      "index": 41,
      "start": 73,
      "stop": 74
    },
    {
      "content": "— C'est qui ?\n— C'était Charles.",
      "index": 42,
      "start": 74,
      "stop": 76
    },
    {
      "content": "— Dis-lui que c'est moi qui ai son portable.\n— Il a raccroché.",
      "index": 43,
      "start": 76,
      "stop": 78
    },
    {
      "content": "— Je l'appelle.",
      "index": 44,
      "start": 78,
      "stop": 79
    },
    {
      "content": "J'ai voulu lui dire qu'il ne pouvait\npas l'appeler vu que c'est lui qui avait\nson portable, mais il avait raccroché.",
      "index": 45,
      "start": 79,
      "stop": 82
    },
    {
      "content": "Pendant ce temps, Ben essayait\nde me reprendre, mais il entendait rien.",
      "index": 46,
      "start": 82,
      "stop": 84
    },
    {
      "content": "Il a raccroché.\nDu coup, j'ai voulu le reprendre.",
      "index": 47,
      "start": 84,
      "stop": 85
    },
    {
      "content": "— Ben ?\nIl y avait plus personne au bout du fil.",
      "index": 48,
      "start": 85,
      "stop": 87
    },
    {
      "content": "Alors j'ai rappelé Ben,\nje suis tombé sur sa messagerie.",
      "index": 49,
      "start": 87,
      "stop": 89
    },
    {
      "content": "— Bon bha, rappelle-moi,\nj'arrive pas à te joindre.",
      "index": 50,
      "start": 89,
      "stop": 91
    },
    {
      "content": "Putain, j'ai compris qu'on était repiégé.",
      "index": 51,
      "start": 91,
      "stop": 92
    },
    {
      "content": "J'ai décidé d'attendre qu'il me rappelle.",
      "index": 52,
      "start": 92,
      "stop": 93
    },
    {
      "content": "Je me suis dit qu'il devait refaire la\nmême chose, alors je l'ai rappelé vite.",
      "index": 53,
      "start": 93,
      "stop": 96
    },
    {
      "content": "— Allô ?\nYes.",
      "index": 54,
      "start": 96,
      "stop": 97
    },
    {
      "content": "C'est pour te dire, il y a Baptiste\nqui essaie de te joindre.",
      "index": 55,
      "start": 97,
      "stop": 99
    },
    {
      "content": "— Ouais, Julien me l'a dit.\n— Je l'appelle.",
      "index": 56,
      "start": 99,
      "stop": 101
    },
    {
      "content": "— Cool, à tout à l'heure.",
      "index": 57,
      "start": 101,
      "stop": 103
    },
    {
      "content": "J'ai raccroché et je savais\ntoujours pas quel film on allait voir.",
      "index": 58,
      "start": 103,
      "stop": 106
    },
    {
      "content": "Bref, j'ai passé un coup de fil.",
      "index": 59,
      "start": 106,
      "stop": 108
    }
  ]
}
