{
  "episode": {
    "duration": "1:50",
    "id": "5U0CfNpXdEc",
    "index": 69,
    "name": "Bref. C'est la merde.",
    "slug": "brefCestLaMerde",
    "viewCount": 6401652
  },
  "subtitles": [
    {
      "content": "Bref, ça faisait huit mois\nque j'étais avec ma copine\net ça se passait super bien.",
      "index": 0,
      "start": 1
    },
    {
      "content": "Quand t'es amoureux, tous les matins, il\ny a une chorégraphie qui se met en place.",
      "index": 1,
      "start": 3
    },
    {
      "content": "— T'as bien dormi ?\n— Ouais.",
      "index": 2,
      "start": 6
    },
    {
      "content": "— Ils sont où les Chocapic ?\n— Je sais pas.",
      "index": 3,
      "start": 7
    },
    {
      "content": "— J'ai ronflé ?\n— Non.",
      "index": 4,
      "start": 10
    },
    {
      "content": "— Tu m'aimes ?\n— Grave.",
      "index": 5,
      "start": 11
    },
    {
      "content": "— Pas autant que moi.\n— Tant mieux.",
      "index": 6,
      "start": 12
    },
    {
      "content": "— Bon bha, j'y vais.\n— Et mon bisou ?",
      "index": 7,
      "start": 14
    },
    {
      "content": "Et puis, un jour, tu sais pas\npourquoi, tout se décale.",
      "index": 8,
      "start": 19
    },
    {
      "content": "— T'as bien dormi ?\n— Non.",
      "index": 9,
      "start": 23
    },
    {
      "content": "— Tu m'aimes ?\n— Je sais pas.",
      "index": 10,
      "start": 25
    },
    {
      "content": "— J'ai ronflé ?\n— Pas autant que moi.",
      "index": 11,
      "start": 27
    },
    {
      "content": "— Grave.\n— Bon bha, j'y vais.",
      "index": 12,
      "start": 28
    },
    {
      "content": "— Tant mieux.\n— Et mon bisou ?",
      "index": 13,
      "start": 30
    },
    {
      "content": "C'était plus comme avant.\nC'était la merde.",
      "index": 14,
      "start": 35
    },
    {
      "content": "Je me demandais si j'étais\nencore amoureux d'elle.",
      "index": 15,
      "start": 36
    },
    {
      "content": "Du coup, j'ai demandé à mes potes\nsi j'étais encore amoureux d'elle.",
      "index": 16,
      "start": 38
    },
    {
      "content": "Ils m'ont répondu:\n— Carrément.\n— Carrément. Enfin...",
      "index": 17,
      "start": 40
    },
    {
      "content": "Je me disais que si je me posais\nla question, c'était mauvais signe.",
      "index": 18,
      "start": 42
    },
    {
      "content": "Je me demandais si le verre était à moitié\nplein ou à moitié vide, mais le problème,\nc'est qu'il l'était à moitié.",
      "index": 19,
      "start": 45
    },
    {
      "content": "Charles m'a dit:\n— Si tu te poses la question, c'est que tu tiens à elle.",
      "index": 20,
      "start": 48
    },
    {
      "content": "Je tenais à elle, comme je tenais à ma\nvieille paire de pump que je mettais plus,\nmes DVD que je regardais jamais\net ma Nintendo qui prenait la poussière.",
      "index": 21,
      "start": 50
    },
    {
      "content": "Et puis mon frère a dit:\n— Bourre-toi la gueule ce soir,\nt'auras ta réponse demain matin.\nSon copain Marc a dit:\n— Oh oui.",
      "index": 22,
      "start": 55
    },
    {
      "content": "Du coup, j'ai appelé le spécialiste\nde ce genre de situation.",
      "index": 23,
      "start": 60
    },
    {
      "content": "— Ouais Ben ? Dis-moi, tu te bourres la gueule\nquel soir pour oublier tes problèmes\navec ta meuf cette semaine ?",
      "index": 24,
      "start": 62
    },
    {
      "content": "— Ce soir ?",
      "index": 25,
      "start": 66
    },
    {
      "content": "— Ok, j'en suis.",
      "index": 26,
      "start": 68
    },
    {
      "content": "Ben m'a emmené dans un bar.",
      "index": 27,
      "start": 69
    },
    {
      "content": "On s'est bourrés la gueule.",
      "index": 28,
      "start": 70
    },
    {
      "content": "Le matin, mes questions étaient\nparties, mes sentiments étaient revenus.",
      "index": 29,
      "start": 71
    },
    {
      "content": "J'avais ma réponse.\nLa chorégraphie pouvait reprendre.",
      "index": 30,
      "start": 75
    },
    {
      "content": "J'ai dit:\n— T'as bien dormi ?",
      "index": 31,
      "start": 77
    },
    {
      "content": "— Ouais.\nMais c'était pas elle.",
      "index": 32,
      "start": 79
    },
    {
      "content": "Bref, c'est la merde.",
      "index": 33,
      "start": 83
    },
    {
      "content": "— Mon verre, il est complètement vide.\n— Attends.",
      "index": 34,
      "start": 88
    },
    {
      "content": "— Je te le transforme en complètement plein.",
      "index": 35,
      "start": 90
    }
  ]
}
